setup.py
pyFrotz.egg-info/PKG-INFO
pyFrotz.egg-info/SOURCES.txt
pyFrotz.egg-info/dependency_links.txt
pyFrotz.egg-info/top_level.txt
pyfrotz/__init__.py