Metadata-Version: 1.0
Name: pyFrotz
Version: 0.1.5
Summary: minimal wrapper around frotz
Home-page: https://github.com/JarbasAl/pyFrotz
Author: jarbasAI
Author-email: jarbasai@mailfence.com
License: MIT
Platform: UNKNOWN
